pycasadi_kin_din.cpython-37m-x86_64-linux-gnu.so
casadi_kin_dyn/__init__.py
casadi_kin_dyn/libcasadi.so.3.7
casadi_kin_dyn/libcasadi_kin_dyn.so.1.6.3
casadi_kin_dyn/libhpp-fcl.so
casadi_kin_dyn/libpinocchio.so.2.6.20
casadi_kin_dyn/py3casadi_kin_dyn.cpython-37m-x86_64-linux-gnu.so
casadi_kin_dyn-1.6.3.dist-info/LICENSE
casadi_kin_dyn-1.6.3.dist-info/METADATA
casadi_kin_dyn-1.6.3.dist-info/WHEEL
casadi_kin_dyn-1.6.3.dist-info/top_level.txt
casadi_kin_dyn-1.6.3.dist-info/RECORD
